<?xml version="1.0" encoding="utf-8" ?>
<dwsync>
<file name="bg.png" server="C:/xampp/htdocs/public_html/ANP/" local="129114990022187504" remote="129114990020000000" />
<file name="header.png" server="C:/xampp/htdocs/public_html/ANP/" local="129122058498605475" remote="129122058490000000" />
<file name="ba106.gif" server="C:/xampp/htdocs/public_html/ANP/" local="129122063634452463" remote="129122063630000000" />
<file name="delete-16x16.png" server="C:/xampp/htdocs/public_html/ANP/" local="129120416520000000" remote="129120416520000000" />
<file name="Printer-icon.png" server="C:/xampp/htdocs/public_html/ANP/" local="129140203540000000" remote="129140203540000000" />
<file name="money_transfer_nml.jpg" server="C:/xampp/htdocs/public_html/ANP/" local="129147123220000000" remote="129147123220000000" />
<file name="transaction_nml.jpg" server="C:/xampp/htdocs/public_html/ANP/" local="129147123980000000" remote="129147123980000000" />
<file name="administrator_nml.jpg" server="C:/xampp/htdocs/public_html/ANP/" local="129147124680000000" remote="129147124680000000" />
<file name="reports_nml.jpg" server="C:/xampp/htdocs/public_html/ANP/" local="129147125480000000" remote="129147125480000000" />
<file name="todaysrates_nml.jpg" server="C:/xampp/htdocs/public_html/ANP/" local="129147128240000000" remote="129147128240000000" />
<file name="help_nml.jpg" server="C:/xampp/htdocs/public_html/ANP/" local="129147128780000000" remote="129147128780000000" />
<file name="logout_nml.jpg" server="C:/xampp/htdocs/public_html/ANP/" local="129147130460000000" remote="129147130460000000" />
<file name="tile_rhs_banner.jpg" server="C:/xampp/htdocs/public_html/ANP/" local="129147168460000000" remote="129147168460000000" />
<file name="topbanner.jpg" server="C:/xampp/htdocs/public_html/ANP/" local="129147170986875000" remote="129147170980000000" />
<file name="menu_after_logout.jpg" server="C:/xampp/htdocs/public_html/ANP/" local="129147196560000000" remote="129147196560000000" />
<file name="button.jpg" server="C:/xampp/htdocs/public_html/ANP/" local="129151371569531250" remote="129151371560000000" />
<file name="B.png" server="C:/xampp/htdocs/public_html/ANP/" local="129145403300000000" remote="129145403300000000" />
<file name="modify_user.jpg" server="C:/xampp/htdocs/public_html/ANP/" local="129152359427187504" remote="129152359420000000" />
<file name="delete_user.jpg" server="C:/xampp/htdocs/public_html/ANP/" local="129152359244218752" remote="129152359240000000" />
<file name="register_agent.jpg" server="C:/xampp/htdocs/public_html/ANP/" local="129152355985312500" remote="129152355980000000" />
<file name="modify_agent.jpg" server="C:/xampp/htdocs/public_html/ANP/" local="129152353501250000" remote="129152353500000000" />
<file name="ANP-logo.jpg" server="C:/xampp/htdocs/public_html/ANP/" local="129153234168125000" remote="129153234160000000" />
</dwsync>